pytest_testrail_integrator/__init__.py
pytest_testrail_integrator/client.py
pytest_testrail_integrator/config.py
pytest_testrail_integrator/constants.py
pytest_testrail_integrator/dto.py
pytest_testrail_integrator/new_hooks.py
pytest_testrail_integrator/plugin.py
pytest_testrail_integrator/service.py
pytest_testrail_integrator/xdist/__init__.py
pytest_testrail_integrator/xdist/xdist_tr_adapter.py
pytest_testrail_integrator-1.2.2.dist-info/LICENSE
pytest_testrail_integrator-1.2.2.dist-info/METADATA
pytest_testrail_integrator-1.2.2.dist-info/WHEEL
pytest_testrail_integrator-1.2.2.dist-info/entry_points.txt
pytest_testrail_integrator-1.2.2.dist-info/top_level.txt
pytest_testrail_integrator-1.2.2.dist-info/RECORD
