Metadata-Version: 2.1
Name: pytest-testrail-integrator
Version: 1.2.2
Summary: Pytest plugin for sending report to testrail system.
Home-page: https://github.com/VStoilovskyi/pytest-testrail-reporter
License: MIT
Keywords: report,pytest,testrail
Classifier: Framework :: Pytest
Classifier: Programming Language :: Python :: 3.8
Classifier: Programming Language :: Python :: 3.9
License-File: LICENSE
Requires-Dist: pytest (>=6.2.5)
Requires-Dist: testrail-api
Requires-Dist: pydash
